clonify/__init__.py
clonify/_native.abi3.so
clonify/cli.py
clonify/clonify.py
clonify/cluster.cpp
clonify/naming.py
clonify/version.py
clonify_antibody-0.1.0.dist-info/METADATA
clonify_antibody-0.1.0.dist-info/WHEEL
clonify_antibody-0.1.0.dist-info/entry_points.txt
clonify_antibody-0.1.0.dist-info/licenses/LICENSE
clonify_antibody-0.1.0.dist-info/RECORD
