Metadata-Version: 2.4
Name: clonify-antibody
Version: 0.1.0
Classifier: Programming Language :: Python
Classifier: Programming Language :: Rust
Classifier: Operating System :: MacOS
Classifier: Operating System :: POSIX :: Linux
Requires-Dist: polars>=0.20
Requires-Dist: mnemonic>=0.20
Requires-Dist: natsort>=8.0
Requires-Dist: click>=8.1
Requires-Dist: maturin>=1.5,<2.0 ; extra == 'dev'
Requires-Dist: pytest>=7.0 ; extra == 'dev'
Requires-Dist: polars>=0.20 ; extra == 'dev'
Requires-Dist: numpy>=1.23 ; extra == 'dev'
Requires-Dist: mnemonic>=0.20 ; extra == 'dev'
Requires-Dist: natsort>=8.0 ; extra == 'dev'
Provides-Extra: dev
License-File: LICENSE
Summary: High-performance clonify implementation with native average-linkage clustering
Author: Bryan Briney
Requires-Python: >=3.10
